{  "1": {    "ID": 1,    "BANK LIST": "",    "Retail Category": ""  },  "2": {    "ID": 2,    "BANK LIST": "24 Hour Fitness",    "Retail Category": "Personal Care"  },  "3": {    "ID": 3,    "BANK LIST": "Kay Jewelers",    "Retail Category": "Clothing/Shoes"  },  "4": {    "ID": 4,    "BANK LIST": "Amazon.com",    "Retail Category": "General Merchandise"  },  "5": {    "ID": 5,    "BANK LIST": "Walmart",    "Retail Category": "General Merchandise"  },  "6": {    "ID": 6,    "BANK LIST": "Apple Inc.",    "Retail Category": "Electronics"  },  "7": {    "ID": 7,    "BANK LIST": "Target",    "Retail Category": "General Merchandise"  },  "8": {    "ID": 8,    "BANK LIST": "Shell",    "Retail Category": "Gasoline/Fuel"  },  "9": {    "ID": 9,    "BANK LIST": "Mcdonald's",    "Retail Category": "Restaurants/Dining"  },  "10": {    "ID": 10,    "BANK LIST": "Starbucks",    "Retail Category": "Restaurants/Dining"  },  "11": {    "ID": 11,    "BANK LIST": "Walgreens",    "Retail Category": "Healthcare/Medical"  },  "12": {    "ID": 12,    "BANK LIST": "Exxon Mobil",    "Retail Category": "Gasoline/Fuel"  },  "13": {    "ID": 13,    "BANK LIST": "Whole Foods",    "Retail Category": "Groceries"  },  "14": {    "ID": 14,    "BANK LIST": "Netflix",    "Retail Category": "Entertainment"  },  "15": {    "ID": 15,    "BANK LIST": "Lowe's",    "Retail Category": "Home Improvement"  },  "16": {    "ID": 16,    "BANK LIST": "CVS Pharmacy",    "Retail Category": "Healthcare/Medical"  },  "17": {    "ID": 17,    "BANK LIST": "Subway",    "Retail Category": "Restaurants/Dining"  },  "18": {    "ID": 18,    "BANK LIST": "Safeway",    "Retail Category": "Groceries"  },  "19": {    "ID": 19,    "BANK LIST": "Kroger",    "Retail Category": "Groceries"  },  "20": {    "ID": 20,    "BANK LIST": "Publix Super Markets",    "Retail Category": "Groceries"  },  "21": {    "ID": 21,    "BANK LIST": "Home Depot",    "Retail Category": "Home Improvement"  },  "22": {    "ID": 22,    "BANK LIST": "Chevron",    "Retail Category": "Gasoline/Fuel"  },  "23": {    "ID": 23,    "BANK LIST": "7-Eleven",    "Retail Category": "Groceries"  },  "24": {    "ID": 24,    "BANK LIST": "Paypal",    "Retail Category": "Transfers"  },  "25": {    "ID": 25,    "BANK LIST": "Army and Air Force Exchange Service",    "Retail Category": "General Merchandise"  },  "26": {    "ID": 26,    "BANK LIST": "Trader Joe's",    "Retail Category": "Groceries"  },  "27": {    "ID": 27,    "BANK LIST": "AT&T",    "Retail Category": "Telephone Services"  },  "28": {    "ID": 28,    "BANK LIST": "USPS",    "Retail Category": "Postage and Shipping"  },  "29": {    "ID": 29,    "BANK LIST": "Seaworld",    "Retail Category": "Entertainment"  },  "30": {    "ID": 30,    "BANK LIST": "Marine Corps Community Services",    "Retail Category": "General Merchandise"  },  "31": {    "ID": 31,    "BANK LIST": "Dunkin' Donuts",    "Retail Category": "Restaurants/Dining"  },  "32": {    "ID": 32,    "BANK LIST": "Amazon Kindle",    "Retail Category": "Entertainment"  },  "33": {    "ID": 33,    "BANK LIST": "Sam's Club",    "Retail Category": "General Merchandise"  },  "34": {    "ID": 34,    "BANK LIST": "Chipotle",    "Retail Category": "Restaurants/Dining"  },  "35": {    "ID": 35,    "BANK LIST": "NYC Taxi",    "Retail Category": "Travel"  },  "36": {    "ID": 36,    "BANK LIST": "Sunoco",    "Retail Category": "Gasoline/Fuel"  },  "37": {    "ID": 37,    "BANK LIST": "Panera Bread",    "Retail Category": "Restaurants/Dining"  },  "38": {    "ID": 38,    "BANK LIST": "Redbox",    "Retail Category": "Entertainment"  },  "39": {    "ID": 39,    "BANK LIST": "Wendy's",    "Retail Category": "Restaurants/Dining"  },  "40": {    "ID": 40,    "BANK LIST": "H-E-B",    "Retail Category": "Groceries"  },  "41": {    "ID": 41,    "BANK LIST": "Rite Aid",    "Retail Category": "Healthcare/Medical"  },  "42": {    "ID": 42,    "BANK LIST": "Barnes & Noble",    "Retail Category": "Hobbies"  },  "43": {    "ID": 43,    "BANK LIST": "Taco Bell",    "Retail Category": "Restaurants/Dining"  },  "44": {    "ID": 44,    "BANK LIST": "Costco",    "Retail Category": "General Merchandise"  },  "45": {    "ID": 45,    "BANK LIST": "Macy's",    "Retail Category": "Clothing/Shoes"  },  "46": {    "ID": 46,    "BANK LIST": "Bed Bath & Beyond",    "Retail Category": "Home Improvement"  },  "47": {    "ID": 47,    "BANK LIST": "Stop & Shop",    "Retail Category": "Groceries"  },  "48": {    "ID": 48,    "BANK LIST": "Verizon Wireless",    "Retail Category": "Telephone Services"  },  "49": {    "ID": 49,    "BANK LIST": "Experian",    "Retail Category": "Online Services"  },  "50": {    "ID": 50,    "BANK LIST": "Uber",    "Retail Category": "Travel"  },  "51": {    "ID": 51,    "BANK LIST": "Best Buy",    "Retail Category": "Electronics"  },  "52": {    "ID": 52,    "BANK LIST": "Burger King",    "Retail Category": "Restaurants/Dining"  },  "53": {    "ID": 53,    "BANK LIST": "Harris Teeter",    "Retail Category": "Groceries"  },  "54": {    "ID": 54,    "BANK LIST": "Groupon",    "Retail Category": "General Merchandise"  },  "55": {    "ID": 55,    "BANK LIST": "Nordstrom",    "Retail Category": "Clothing/Shoes"  },  "56": {    "ID": 56,    "BANK LIST": "Chick-fil-A",    "Retail Category": "Restaurants/Dining"  },  "57": {    "ID": 57,    "BANK LIST": "E-ZPass",    "Retail Category": "Travel"  },  "58": {    "ID": 58,    "BANK LIST": "Wawa Inc.",    "Retail Category": "Groceries"  },  "59": {    "ID": 59,    "BANK LIST": "T.J.Maxx",    "Retail Category": "Clothing/Shoes"  },  "60": {    "ID": 60,    "BANK LIST": "Aramark",    "Retail Category": "General Merchandise"  },  "61": {    "ID": 61,    "BANK LIST": "Marshalls",    "Retail Category": "General Merchandise"  },  "62": {    "ID": 62,    "BANK LIST": "Staples",    "Retail Category": "Office Supplies"  },  "63": {    "ID": 63,    "BANK LIST": "Metropolitan Transportation Authority",    "Retail Category": "Travel"  },  "64": {    "ID": 64,    "BANK LIST": "Carrabba's Italian Grill",    "Retail Category": "Restaurants/Dining"  },  "65": {    "ID": 65,    "BANK LIST": "Hot Topic",    "Retail Category": "Clothing/Shoes"  },  "66": {    "ID": 66,    "BANK LIST": "Albertsons",    "Retail Category": "Groceries"  },  "67": {    "ID": 67,    "BANK LIST": "Shoprite",    "Retail Category": "Groceries"  },  "68": {    "ID": 68,    "BANK LIST": "Ralphs",    "Retail Category": "Groceries"  },  "69": {    "ID": 69,    "BANK LIST": "Duane Reade",    "Retail Category": "Healthcare/Medical"  },  "70": {    "ID": 70,    "BANK LIST": "Michaels",    "Retail Category": "Hobbies"  },  "71": {    "ID": 71,    "BANK LIST": "Petsmart",    "Retail Category": "Pets/Pet Care"  },  "72": {    "ID": 72,    "BANK LIST": "Comcast",    "Retail Category": "Cable/Satellite Services"  },  "73": {    "ID": 73,    "BANK LIST": "Southwest Airlines",    "Retail Category": "Travel"  },  "74": {    "ID": 74,    "BANK LIST": "Capital One",    "Retail Category": "Use Subtype Rules for Categories"  },  "75": {    "ID": 75,    "BANK LIST": "Giant Food",    "Retail Category": "Groceries"  },  "76": {    "ID": 76,    "BANK LIST": "Ross Stores Inc.",    "Retail Category": "Clothing/Shoes"  },  "77": {    "ID": 77,    "BANK LIST": "Kohl's",    "Retail Category": "General Merchandise"  },  "78": {    "ID": 78,    "BANK LIST": "Food Lion",    "Retail Category": "Groceries"  },  "79": {    "ID": 79,    "BANK LIST": "J. C. Penney",    "Retail Category": "Clothing/Shoes"  },  "80": {    "ID": 80,    "BANK LIST": "Journeys",    "Retail Category": "Clothing/Shoes"  },  "81": {    "ID": 81,    "BANK LIST": "BJ's Wholesale Club",    "Retail Category": "General Merchandise"  },  "82": {    "ID": 82,    "BANK LIST": "Wegmans",    "Retail Category": "Home Improvement"  },  "83": {    "ID": 83,    "BANK LIST": "Navy Exchange",    "Retail Category": "General Merchandise"  },  "84": {    "ID": 84,    "BANK LIST": "Virginia Department of Alcoholic Beverage Control",    "Retail Category": "Other Expenses"  },  "85": {    "ID": 85,    "BANK LIST": "Costco Gas",    "Retail Category": "Gasoline/Fuel"  },  "86": {    "ID": 86,    "BANK LIST": "Domino's Pizza",    "Retail Category": "Restaurants/Dining"  },  "87": {    "ID": 87,    "BANK LIST": "MassMutual",    "Retail Category": "Insurance"  },  "88": {    "ID": 88,    "BANK LIST": "Meijer",    "Retail Category": "Groceries"  },  "89": {    "ID": 89,    "BANK LIST": "Old Navy",    "Retail Category": "Clothing/Shoes"  },  "90": {    "ID": 90,    "BANK LIST": "Fedex",    "Retail Category": "Postage and Shipping"  },  "91": {    "ID": 91,    "BANK LIST": "Gulf Oil LP",    "Retail Category": "Gasoline/Fuel"  },  "92": {    "ID": 92,    "BANK LIST": "Sears",    "Retail Category": "General Merchandise"  },  "93": {    "ID": 93,    "BANK LIST": "Vons",    "Retail Category": "Groceries"  },  "94": {    "ID": 94,    "BANK LIST": "Circle K",    "Retail Category": "Gasoline/Fuel"  },  "95": {    "ID": 95,    "BANK LIST": "DirecTV",    "Retail Category": "Cable/Satellite Services"  },  "96": {    "ID": 96,    "BANK LIST": "Dollar Tree",    "Retail Category": "General Merchandise"  },  "97": {    "ID": 97,    "BANK LIST": "T-Mobile",    "Retail Category": "Telephone Services"  },  "98": {    "ID": 98,    "BANK LIST": "Time Warner Cable",    "Retail Category": "Cable/Satellite Services"  },  "99": {    "ID": 99,    "BANK LIST": "US Airways",    "Retail Category": "Travel"  },  "100": {    "ID": 100,    "BANK LIST": "Papa John's Pizza",    "Retail Category": "Restaurants/Dining"  },  "101": {    "ID": 101,    "BANK LIST": "Snack & Soda Vending",    "Retail Category": "Groceries"  },  "102": {    "ID": 102,    "BANK LIST": "Petco's",    "Retail Category": "Pets/Pet Care"  },  "103": {    "ID": 103,    "BANK LIST": "Jimmy John's",    "Retail Category": "Restaurants/Dining"  },  "104": {    "ID": 104,    "BANK LIST": "IKEA",    "Retail Category": "Home Improvement"  },  "105": {    "ID": 105,    "BANK LIST": "Hess Corporation",    "Retail Category": "Gasoline/Fuel"  },  "106": {    "ID": 106,    "BANK LIST": "Pizza Hut",    "Retail Category": "Restaurants/Dining"  },  "107": {    "ID": 107,    "BANK LIST": "Sheetz",    "Retail Category": "Gasoline/Fuel"  },  "108": {    "ID": 108,    "BANK LIST": "Toys 'R' Us",    "Retail Category": "Child/Dependent Expenses"  },  "109": {    "ID": 109,    "BANK LIST": "USAA",    "Retail Category": "Use Subtype Rules for Categories"  },  "110": {    "ID": 110,    "BANK LIST": "RaceTrac",    "Retail Category": "Gasoline/Fuel"  },  "111": {    "ID": 111,    "BANK LIST": "Fred Meyer",    "Retail Category": "Groceries"  },  "112": {    "ID": 112,    "BANK LIST": "Panda Express",    "Retail Category": "Restaurants/Dining"  },  "113": {    "ID": 113,    "BANK LIST": "Sprout's Farmers Market",    "Retail Category": "Groceries"  },  "114": {    "ID": 114,    "BANK LIST": "Victoria's Secret",    "Retail Category": "Clothing/Shoes"  },  "115": {    "ID": 115,    "BANK LIST": "Gap Inc.",    "Retail Category": "Clothing/Shoes"  },  "116": {    "ID": 116,    "BANK LIST": "Sonic Drive-In",    "Retail Category": "Restaurants/Dining"  },  "117": {    "ID": 117,    "BANK LIST": "Delta Air Lines",    "Retail Category": "Travel"  },  "118": {    "ID": 118,    "BANK LIST": "KFC",    "Retail Category": "Restaurants/Dining"  },  "119": {    "ID": 119,    "BANK LIST": "Chili's",    "Retail Category": "Restaurants/Dining"  },  "120": {    "ID": 120,    "BANK LIST": "QVC",    "Retail Category": "Cable/Satellite Services"  },  "121": {    "ID": 121,    "BANK LIST": "King Soopers",    "Retail Category": "Groceries"  },  "122": {    "ID": 122,    "BANK LIST": "Kmart",    "Retail Category": "General Merchandise"  },  "123": {    "ID": 123,    "BANK LIST": "AutoZone",    "Retail Category": "Automotive Expenses"  },  "124": {    "ID": 124,    "BANK LIST": "Seamless",    "Retail Category": "Restaurants/Dining"  },  "125": {    "ID": 125,    "BANK LIST": "Google",    "Retail Category": "Online Services"  },  "126": {    "ID": 126,    "BANK LIST": "Corner Store",    "Retail Category": "Restaurants/Dining"  },  "127": {    "ID": 127,    "BANK LIST": "Regal Cinemas",    "Retail Category": "Entertainment"  },  "128": {    "ID": 128,    "BANK LIST": "Office Depot",    "Retail Category": "Office Supplies"  },  "129": {    "ID": 129,    "BANK LIST": "The UPS Store",    "Retail Category": "Postage and Shipping"  },  "130": {    "ID": 130,    "BANK LIST": "Sprint",    "Retail Category": "Telephone Services"  },  "131": {    "ID": 131,    "BANK LIST": "Winn-Dixie",    "Retail Category": "Groceries"  },  "132": {    "ID": 132,    "BANK LIST": "Arby's",    "Retail Category": "Restaurants/Dining"  },  "133": {    "ID": 133,    "BANK LIST": "Hobby Lobby",    "Retail Category": "Hobbies"  },  "134": {    "ID": 134,    "BANK LIST": "Sirius XM",    "Retail Category": "Entertainment"  },  "135": {    "ID": 135,    "BANK LIST": "Kangaroo Express",    "Retail Category": "Groceries"  },  "136": {    "ID": 136,    "BANK LIST": "Valero",    "Retail Category": "Gasoline/Fuel"  },  "137": {    "ID": 137,    "BANK LIST": "In-N-Out Burger",    "Retail Category": "Restaurants/Dining"  },  "138": {    "ID": 138,    "BANK LIST": "American Airlines",    "Retail Category": "Travel"  },  "139": {    "ID": 139,    "BANK LIST": "Pilot Flying J",    "Retail Category": "Travel"  },  "140": {    "ID": 140,    "BANK LIST": "Hulu",    "Retail Category": "Entertainment"  },  "141": {    "ID": 141,    "BANK LIST": "Xbox",    "Retail Category": "Entertainment"  },  "142": {    "ID": 142,    "BANK LIST": "Sephora",    "Retail Category": "Personal Care"  },  "143": {    "ID": 143,    "BANK LIST": "Zappos",    "Retail Category": "Clothing/Shoes"  },  "144": {    "ID": 144,    "BANK LIST": "Marriott Hotels",    "Retail Category": "Travel"  },  "145": {    "ID": 145,    "BANK LIST": "Applebee's",    "Retail Category": "Restaurants/Dining"  },  "146": {    "ID": 146,    "BANK LIST": "Five Guys",    "Retail Category": "Restaurants/Dining"  },  "147": {    "ID": 147,    "BANK LIST": "ADT Security",    "Retail Category": "Home Maintenance"  },  "148": {    "ID": 148,    "BANK LIST": "Olive Garden",    "Retail Category": "Restaurants/Dining"  },  "149": {    "ID": 149,    "BANK LIST": "Florida Power & Light",    "Retail Category": "Utilities"  },  "150": {    "ID": 150,    "BANK LIST": "Banana Republic",    "Retail Category": "Clothing/Shoes"  },  "151": {    "ID": 151,    "BANK LIST": "Dairy Queen",    "Retail Category": "Restaurants/Dining"  },  "152": {    "ID": 152,    "BANK LIST": "REI",    "Retail Category": "Clothing/Shoes"  },  "153": {    "ID": 153,    "BANK LIST": "J.Crew",    "Retail Category": "Clothing/Shoes"  },  "154": {    "ID": 154,    "BANK LIST": "Jo-Ann Fabric and Craft Stores",    "Retail Category": "Hobbies"  },  "155": {    "ID": 155,    "BANK LIST": "IHOP",    "Retail Category": "Restaurants/Dining"  },  "156": {    "ID": 156,    "BANK LIST": "H&M",    "Retail Category": "Clothing/Shoes"  },  "157": {    "ID": 157,    "BANK LIST": "The Sports Authority",    "Retail Category": "General Merchandise"  },  "158": {    "ID": 158,    "BANK LIST": "Dillard's",    "Retail Category": "Clothing/Shoes"  },  "159": {    "ID": 159,    "BANK LIST": "Audible Inc.",    "Retail Category": "Entertainment"  },  "160": {    "ID": 160,    "BANK LIST": "Coca Cola",    "Retail Category": "Restaurants/Dining"  },  "161": {    "ID": 161,    "BANK LIST": "Whataburger",    "Retail Category": "Restaurants/Dining"  },  "162": {    "ID": 162,    "BANK LIST": "The New York Times",    "Retail Category": "Hobbies"  },  "163": {    "ID": 163,    "BANK LIST": "Ace Hardware",    "Retail Category": "Home Maintenance"  },  "164": {    "ID": 164,    "BANK LIST": "Tom Thumb",    "Retail Category": "Groceries"  },  "165": {    "ID": 165,    "BANK LIST": "Massage Envy",    "Retail Category": "Personal Care"  },  "166": {    "ID": 166,    "BANK LIST": "Charlotte Russe",    "Retail Category": "Clothing/Shoes"  },  "167": {    "ID": 167,    "BANK LIST": "Geico",    "Retail Category": "Insurance"  },  "168": {    "ID": 168,    "BANK LIST": "Ulta",    "Retail Category": "Personal Care"  },  "169": {    "ID": 169,    "BANK LIST": "DSW",    "Retail Category": "Clothing/Shoes"  },  "170": {    "ID": 170,    "BANK LIST": "Dollar General Store",    "Retail Category": "General Merchandise"  },  "171": {    "ID": 171,    "BANK LIST": "Dish Network",    "Retail Category": "Cable/Satellite Services"  },  "172": {    "ID": 172,    "BANK LIST": "LA Fitness",    "Retail Category": "Personal Care"  },  "173": {    "ID": 173,    "BANK LIST": "Texaco",    "Retail Category": "Gasoline/Fuel"  },  "174": {    "ID": 174,    "BANK LIST": "Ann Taylor",    "Retail Category": "Clothing/Shoes"  },  "175": {    "ID": 175,    "BANK LIST": "YMCA",    "Retail Category": "Charitable Giving"  },  "176": {    "ID": 176,    "BANK LIST": "Hilton Hotels & Resorts",    "Retail Category": "Travel"  },  "177": {    "ID": 177,    "BANK LIST": "Menards",    "Retail Category": "Home Improvement"  },  "178": {    "ID": 178,    "BANK LIST": "Au Bon Pain",    "Retail Category": "Restaurants/Dining"  },  "179": {    "ID": 179,    "BANK LIST": "Citgo",    "Retail Category": "Gasoline/Fuel"  },  "180": {    "ID": 180,    "BANK LIST": "Great Clips",    "Retail Category": "Personal Care"  },  "181": {    "ID": 181,    "BANK LIST": "Cracker Barrel",    "Retail Category": "Restaurants/Dining"  },  "182": {    "ID": 182,    "BANK LIST": "Dick's Sporting Goods",    "Retail Category": "General Merchandise"  },  "183": {    "ID": 183,    "BANK LIST": "Potbelly",    "Retail Category": "Restaurants/Dining"  },  "184": {    "ID": 184,    "BANK LIST": "Amtrak",    "Retail Category": "Travel"  },  "185": {    "ID": 185,    "BANK LIST": "Popeyes Louisiana Kitchen",    "Retail Category": "Restaurants/Dining"  },  "186": {    "ID": 186,    "BANK LIST": "Key Food",    "Retail Category": "Groceries"  },  "187": {    "ID": 187,    "BANK LIST": "Bealls",    "Retail Category": "Clothing/Shoes"  },  "188": {    "ID": 188,    "BANK LIST": "Big Lots",    "Retail Category": "Home Improvement"  },  "189": {    "ID": 189,    "BANK LIST": "Hannaford",    "Retail Category": "Groceries"  },  "190": {    "ID": 190,    "BANK LIST": "Hy-Vee",    "Retail Category": "Groceries"  },  "191": {    "ID": 191,    "BANK LIST": "Amazon Digital Services",    "Retail Category": "Entertainment"  },  "192": {    "ID": 192,    "BANK LIST": "Alaska Airlines",    "Retail Category": "Travel"  },  "193": {    "ID": 193,    "BANK LIST": "Jetblue",    "Retail Category": "Travel"  },  "194": {    "ID": 194,    "BANK LIST": "Pret a Manger",    "Retail Category": "Restaurants/Dining"  },  "195": {    "ID": 195,    "BANK LIST": "Hudson Group",    "Retail Category": "Travel"  },  "196": {    "ID": 196,    "BANK LIST": "Party City",    "Retail Category": "Gifts"  },  "197": {    "ID": 197,    "BANK LIST": "The Fresh Market",    "Retail Category": "Groceries"  },  "198": {    "ID": 198,    "BANK LIST": "Advance Auto Parts",    "Retail Category": "Automotive Expenses"  },  "199": {    "ID": 199,    "BANK LIST": "Safeway Fuel",    "Retail Category": "Gasoline/Fuel"  },  "200": {    "ID": 200,    "BANK LIST": "Gamestop",    "Retail Category": "Entertainment"  },  "201": {    "ID": 201,    "BANK LIST": "Dunkin' Donuts / Baskin-Robbins",    "Retail Category": "Restaurants/Dining"  },  "202": {    "ID": 202,    "BANK LIST": "Sallie Mae",    "Retail Category": "Loans"  },  "203": {    "ID": 203,    "BANK LIST": "Radioshack",    "Retail Category": "Electronics"  },  "204": {    "ID": 204,    "BANK LIST": "Long John Silver's",    "Retail Category": "Restaurants/Dining"  },  "205": {    "ID": 205,    "BANK LIST": "Fairway Market",    "Retail Category": "Groceries"  },  "206": {    "ID": 206,    "BANK LIST": "GNC",    "Retail Category": "Healthcare/Medical"  },  "207": {    "ID": 207,    "BANK LIST": "Love's",    "Retail Category": "Groceries"  },  "208": {    "ID": 208,    "BANK LIST": "Facebook",    "Retail Category": "Online Services"  },  "209": {    "ID": 209,    "BANK LIST": "Outback Steakhouse",    "Retail Category": "Restaurants/Dining"  },  "210": {    "ID": 210,    "BANK LIST": "OfficeMax",    "Retail Category": "Office Supplies"  },  "211": {    "ID": 211,    "BANK LIST": "Academy Sports + Outdoors",    "Retail Category": "Hobbies"  },  "212": {    "ID": 212,    "BANK LIST": "BJ's Wholesale Club Fuel",    "Retail Category": "Gasoline/Fuel"  },  "213": {    "ID": 213,    "BANK LIST": "Jack in the Box",    "Retail Category": "Restaurants/Dining"  },  "214": {    "ID": 214,    "BANK LIST": "O'Reilly Auto Parts",    "Retail Category": "Automotive Expenses"  },  "215": {    "ID": 215,    "BANK LIST": "Holiday Inn",    "Retail Category": "Travel"  },  "216": {    "ID": 216,    "BANK LIST": "Skype",    "Retail Category": "Online Services"  },  "217": {    "ID": 217,    "BANK LIST": "Little Caesars",    "Retail Category": "Restaurants/Dining"  },  "218": {    "ID": 218,    "BANK LIST": "Peet's Coffee & Tea",    "Retail Category": "Restaurants/Dining"  },  "219": {    "ID": 219,    "BANK LIST": "Forever 21",    "Retail Category": "Clothing/Shoes"  },  "220": {    "ID": 220,    "BANK LIST": "Bloomingdale's",    "Retail Category": "Clothing/Shoes"  },  "221": {    "ID": 221,    "BANK LIST": "American Eagle Outfitters",    "Retail Category": "Clothing/Shoes"  },  "222": {    "ID": 222,    "BANK LIST": "Giant Eagle",    "Retail Category": "Groceries"  },  "223": {    "ID": 223,    "BANK LIST": "Jamba Juice",    "Retail Category": "Restaurants/Dining"  },  "224": {    "ID": 224,    "BANK LIST": "Washington Metropolitan Area Transit Authority",    "Retail Category": "Travel"  },  "225": {    "ID": 225,    "BANK LIST": "QFC",    "Retail Category": "Groceries"  },  "226": {    "ID": 226,    "BANK LIST": "LivingSocial Inc.",    "Retail Category": "Online Services"  },  "227": {    "ID": 227,    "BANK LIST": "Cinemark Theatres",    "Retail Category": "Entertainment"  },  "228": {    "ID": 228,    "BANK LIST": "Weight Watchers",    "Retail Category": "Personal Care"  },  "229": {    "ID": 229,    "BANK LIST": "Hyatt",    "Retail Category": "Travel"  },  "230": {    "ID": 230,    "BANK LIST": "Fandango",    "Retail Category": "Entertainment"  },  "231": {    "ID": 231,    "BANK LIST": "Fry's Food and Drug",    "Retail Category": "Groceries"  },  "232": {    "ID": 232,    "BANK LIST": "United Airlines",    "Retail Category": "Travel"  },  "233": {    "ID": 233,    "BANK LIST": "The Food Emporium",    "Retail Category": "Groceries"  },  "234": {    "ID": 234,    "BANK LIST": "Total Wine & More",    "Retail Category": "Groceries"  },  "235": {    "ID": 235,    "BANK LIST": "Buffalo Wild Wings",    "Retail Category": "Restaurants/Dining"  },  "236": {    "ID": 236,    "BANK LIST": "Red Robin",    "Retail Category": "Restaurants/Dining"  },  "237": {    "ID": 237,    "BANK LIST": "SunPass",    "Retail Category": "Travel"  },  "238": {    "ID": 238,    "BANK LIST": "Chrysler",    "Retail Category": "Automotive Expenses"  },  "239": {    "ID": 239,    "BANK LIST": "Etsy Inc.",    "Retail Category": "General Merchandise"  },  "240": {    "ID": 240,    "BANK LIST": "GetGo",    "Retail Category": "Gasoline/Fuel"  },  "241": {    "ID": 241,    "BANK LIST": "H Mart",    "Retail Category": "Groceries"  },  "242": {    "ID": 242,    "BANK LIST": "MTA LIRR",    "Retail Category": "Travel"  },  "243": {    "ID": 243,    "BANK LIST": "Pathmark",    "Retail Category": "Groceries"  },  "244": {    "ID": 244,    "BANK LIST": "State Farm Insurance",    "Retail Category": "Insurance"  },  "245": {    "ID": 245,    "BANK LIST": "Pottery Barn",    "Retail Category": "Home Improvement"  },  "246": {    "ID": 246,    "BANK LIST": "Intuit",    "Retail Category": "Online Services"  },  "247": {    "ID": 247,    "BANK LIST": "Chicken Express",    "Retail Category": "Restaurants/Dining"  },  "248": {    "ID": 248,    "BANK LIST": "Spotify",    "Retail Category": "Entertainment"  },  "249": {    "ID": 249,    "BANK LIST": "Citibank",    "Retail Category": "Use Subtype Rules for Categories"  },  "250": {    "ID": 250,    "BANK LIST": "AAA",    "Retail Category": "Insurance"  },  "251": {    "ID": 251,    "BANK LIST": "Canteen Vending Services",    "Retail Category": "Restaurants/Dining"  },  "252": {    "ID": 252,    "BANK LIST": "Price Chopper",    "Retail Category": "Groceries"  },  "253": {    "ID": 253,    "BANK LIST": "Burlington Coat Factory",    "Retail Category": "Clothing/Shoes"  },  "254": {    "ID": 254,    "BANK LIST": "Fry's Electronics",    "Retail Category": "Entertainment"  },  "255": {    "ID": 255,    "BANK LIST": "Gold's Gym",    "Retail Category": "Personal Care"  },  "256": {    "ID": 256,    "BANK LIST": "Anthropologie",    "Retail Category": "Clothing/Shoes"  },  "257": {    "ID": 257,    "BANK LIST": "Peoples Gas",    "Retail Category": "Utilities"  },  "258": {    "ID": 258,    "BANK LIST": "Progressive Insurance",    "Retail Category": "Insurance"  },  "259": {    "ID": 259,    "BANK LIST": "Quiznos",    "Retail Category": "Restaurants/Dining"  },  "260": {    "ID": 260,    "BANK LIST": "CitiMortgage",    "Retail Category": "Mortgages"  },  "261": {    "ID": 261,    "BANK LIST": "GoDaddy",    "Retail Category": "Online Services"  },  "262": {    "ID": 262,    "BANK LIST": "TGI Fridays",    "Retail Category": "Restaurants/Dining"  },  "263": {    "ID": 263,    "BANK LIST": "OnStar",    "Retail Category": "Automotive Expenses"  },  "264": {    "ID": 264,    "BANK LIST": "Zulily",    "Retail Category": "General Merchandise"  },  "265": {    "ID": 265,    "BANK LIST": "Bath & Body Works",    "Retail Category": "Personal Care"  },  "266": {    "ID": 266,    "BANK LIST": "Waldbaum's",    "Retail Category": "Groceries"  },  "267": {    "ID": 267,    "BANK LIST": "Nike",    "Retail Category": "Clothing/Shoes"  },  "268": {    "ID": 268,    "BANK LIST": "Stater Bros.",    "Retail Category": "Groceries"  },  "269": {    "ID": 269,    "BANK LIST": "UnitedHealthcare",    "Retail Category": "Insurance"  },  "270": {    "ID": 270,    "BANK LIST": "Goodwill",    "Retail Category": "Charitable Giving"  },  "271": {    "ID": 271,    "BANK LIST": "Hallmark",    "Retail Category": "Gifts"  },  "272": {    "ID": 272,    "BANK LIST": "The Paradies Shops",    "Retail Category": "General Merchandise"  },  "273": {    "ID": 273,    "BANK LIST": "Payless ShoeSource",    "Retail Category": "Clothing/Shoes"  },  "274": {    "ID": 274,    "BANK LIST": "Fresh & Easy",    "Retail Category": "Groceries"  },  "275": {    "ID": 275,    "BANK LIST": "DMV",    "Retail Category": "Automotive Expenses"  },  "276": {    "ID": 276,    "BANK LIST": "Home Shopping Network",    "Retail Category": "Cable/Satellite Services"  },  "277": {    "ID": 277,    "BANK LIST": "Steam",    "Retail Category": "Entertainment"  },  "278": {    "ID": 278,    "BANK LIST": "P. F. Chang's",    "Retail Category": "Restaurants/Dining"  },  "279": {    "ID": 279,    "BANK LIST": "Google Midas",    "Retail Category": "Online Services"  },  "280": {    "ID": 280,    "BANK LIST": "Kaiser Permanente",    "Retail Category": "Healthcare/Medical"  },  "281": {    "ID": 281,    "BANK LIST": "GrubHub",    "Retail Category": "Restaurants/Dining"  },  "282": {    "ID": 282,    "BANK LIST": "The Children's Place",    "Retail Category": "Child/Dependent Expenses"  },  "283": {    "ID": 283,    "BANK LIST": "Supercuts",    "Retail Category": "Personal Care"  },  "284": {    "ID": 284,    "BANK LIST": "Central Market",    "Retail Category": "Groceries"  },  "285": {    "ID": 285,    "BANK LIST": "Family Dollar",    "Retail Category": "General Merchandise"  },  "286": {    "ID": 286,    "BANK LIST": "Harbor Freight Tools",    "Retail Category": "Home Maintenance"  },  "287": {    "ID": 287,    "BANK LIST": "Zipcar",    "Retail Category": "Travel"  },  "288": {    "ID": 288,    "BANK LIST": "The Cheesecake Factory",    "Retail Category": "Restaurants/Dining"  },  "289": {    "ID": 289,    "BANK LIST": "Schnucks",    "Retail Category": "Groceries"  },  "290": {    "ID": 290,    "BANK LIST": "Einstein Bros Bagels",    "Retail Category": "Restaurants/Dining"  },  "291": {    "ID": 291,    "BANK LIST": "Microsoft",    "Retail Category": "Online Services"  },  "292": {    "ID": 292,    "BANK LIST": "Gymboree",    "Retail Category": "Child/Dependent Expenses"  },  "293": {    "ID": 293,    "BANK LIST": "Corner Bakery Cafe",    "Retail Category": "Restaurants/Dining"  },  "294": {    "ID": 294,    "BANK LIST": "Straight Talk",    "Retail Category": "Telephone Services"  },  "295": {    "ID": 295,    "BANK LIST": "Yellow Cab Company",    "Retail Category": "Travel"  },  "296": {    "ID": 296,    "BANK LIST": "Chuck E. Cheese's",    "Retail Category": "Restaurants/Dining"  },  "297": {    "ID": 297,    "BANK LIST": "Toyota",    "Retail Category": "Automotive Expenses"  },  "298": {    "ID": 298,    "BANK LIST": "Carter's",    "Retail Category": "Child/Dependent Expenses"  },  "299": {    "ID": 299,    "BANK LIST": "Dominick's",    "Retail Category": "Groceries"  },  "300": {    "ID": 300,    "BANK LIST": "Captain D's",    "Retail Category": "Restaurants/Dining"  },  "301": {    "ID": 301,    "BANK LIST": "Smart & Final",    "Retail Category": "Groceries"  },  "302": {    "ID": 302,    "BANK LIST": "Ruby Tuesday",    "Retail Category": "Restaurants/Dining"  },  "303": {    "ID": 303,    "BANK LIST": "QuikTrip",    "Retail Category": "Groceries"  },  "304": {    "ID": 304,    "BANK LIST": "Hardee's",    "Retail Category": "Restaurants/Dining"  },  "305": {    "ID": 305,    "BANK LIST": "FreshDirect",    "Retail Category": "Groceries"  },  "306": {    "ID": 306,    "BANK LIST": "AOL",    "Retail Category": "Online Services"  },  "307": {    "ID": 307,    "BANK LIST": "Vudu",    "Retail Category": "Entertainment"  },  "308": {    "ID": 308,    "BANK LIST": "Bruegger's",    "Retail Category": "Restaurants/Dining"  },  "309": {    "ID": 309,    "BANK LIST": "Acme Markets",    "Retail Category": "Groceries"  },  "310": {    "ID": 310,    "BANK LIST": "Yogurt Land",    "Retail Category": "Restaurants/Dining"  },  "311": {    "ID": 311,    "BANK LIST": "Honda",    "Retail Category": "Automotive Expenses"  },  "312": {    "ID": 312,    "BANK LIST": "BJ's Restaurant & Brewery",    "Retail Category": "Restaurants/Dining"  },  "313": {    "ID": 313,    "BANK LIST": "Moe's Southwest Grill",    "Retail Category": "Restaurants/Dining"  },  "314": {    "ID": 314,    "BANK LIST": "Shoppers Food & Pharmacy",    "Retail Category": "Groceries"  },  "315": {    "ID": 315,    "BANK LIST": "Mariano's",    "Retail Category": "Groceries"  },  "316": {    "ID": 316,    "BANK LIST": "Woodman's Markets",    "Retail Category": "Groceries"  },  "317": {    "ID": 317,    "BANK LIST": "Lord & Taylor",    "Retail Category": "Clothing/Shoes"  },  "318": {    "ID": 318,    "BANK LIST": "Red Lobster",    "Retail Category": "Restaurants/Dining"  },  "319": {    "ID": 319,    "BANK LIST": "Qdoba Mexican Grill",    "Retail Category": "Restaurants/Dining"  },  "320": {    "ID": 320,    "BANK LIST": "New York City Department of Transportation",    "Retail Category": "Travel"  },  "321": {    "ID": 321,    "BANK LIST": "Cosi",    "Retail Category": "Restaurants/Dining"  },  "322": {    "ID": 322,    "BANK LIST": "Belk",    "Retail Category": "Clothing/Shoes"  },  "323": {    "ID": 323,    "BANK LIST": "Thorntons",    "Retail Category": "General Merchandise"  },  "324": {    "ID": 324,    "BANK LIST": "Tractor Supply Company",    "Retail Category": "Automotive Expenses"  },  "325": {    "ID": 325,    "BANK LIST": "MAPCO",    "Retail Category": "Groceries"  },  "326": {    "ID": 326,    "BANK LIST": "Jersey Mike's Subs",    "Retail Category": "Restaurants/Dining"  },  "327": {    "ID": 327,    "BANK LIST": "MetLife",    "Retail Category": "Insurance"  },  "328": {    "ID": 328,    "BANK LIST": "Firehouse Subs",    "Retail Category": "Restaurants/Dining"  },  "329": {    "ID": 329,    "BANK LIST": "Texas Roadhouse",    "Retail Category": "Restaurants/Dining"  },  "330": {    "ID": 330,    "BANK LIST": "Gristede's",    "Retail Category": "Groceries"  },  "331": {    "ID": 331,    "BANK LIST": "Zaxby's",    "Retail Category": "Restaurants/Dining"  },  "332": {    "ID": 332,    "BANK LIST": "Randall's",    "Retail Category": "Groceries"  },  "333": {    "ID": 333,    "BANK LIST": "Blizzard Entertainment",    "Retail Category": "Entertainment"  },  "334": {    "ID": 334,    "BANK LIST": "Royal Farms",    "Retail Category": "Groceries"  },  "335": {    "ID": 335,    "BANK LIST": "Lukoil",    "Retail Category": "Gasoline/Fuel"  },  "336": {    "ID": 336,    "BANK LIST": "Brookshire's",    "Retail Category": "Groceries"  },  "337": {    "ID": 337,    "BANK LIST": "Jason's Deli",    "Retail Category": "Restaurants/Dining"  },  "338": {    "ID": 338,    "BANK LIST": "Rubio's",    "Retail Category": "Restaurants/Dining"  },  "339": {    "ID": 339,    "BANK LIST": "Pei Wei",    "Retail Category": "Restaurants/Dining"  },  "340": {    "ID": 340,    "BANK LIST": "Noodles & Company",    "Retail Category": "Restaurants/Dining"  },  "341": {    "ID": 341,    "BANK LIST": "Enterprise Rent-A-Car",    "Retail Category": "Travel"  },  "342": {    "ID": 342,    "BANK LIST": "Eurest Dining",    "Retail Category": "Restaurants/Dining"  },  "343": {    "ID": 343,    "BANK LIST": "Playstation Network",    "Retail Category": "Entertainment"  },  "344": {    "ID": 344,    "BANK LIST": "U-Haul",    "Retail Category": "Travel"  },  "345": {    "ID": 345,    "BANK LIST": "Pier 1 Imports",    "Retail Category": "Home Improvement"  },  "346": {    "ID": 346,    "BANK LIST": "North Texas Tollway Authority",    "Retail Category": "Travel"  },  "347": {    "ID": 347,    "BANK LIST": "Sally Beauty Supply",    "Retail Category": "Personal Care"  },  "348": {    "ID": 348,    "BANK LIST": "Lending Club",    "Retail Category": "Online Services"  },  "349": {    "ID": 349,    "BANK LIST": "Century Theatres",    "Retail Category": "Entertainment"  },  "350": {    "ID": 350,    "BANK LIST": "Ingles Markets",    "Retail Category": "Groceries"  },  "351": {    "ID": 351,    "BANK LIST": "Banfield",    "Retail Category": "Pets/Pet Care"  },  "352": {    "ID": 352,    "BANK LIST": "New Jersey Transit",    "Retail Category": "Travel"  },  "353": {    "ID": 353,    "BANK LIST": "Stubhub",    "Retail Category": "Entertainment"  },  "354": {    "ID": 354,    "BANK LIST": "CVS Caremark",    "Retail Category": "Healthcare/Medical"  },  "355": {    "ID": 355,    "BANK LIST": "Raley's",    "Retail Category": "Groceries"  },  "356": {    "ID": 356,    "BANK LIST": "Culver's",    "Retail Category": "Restaurants/Dining"  },  "357": {    "ID": 357,    "BANK LIST": "A&P",    "Retail Category": "Groceries"  },  "358": {    "ID": 358,    "BANK LIST": "Kwik Trip",    "Retail Category": "Gasoline/Fuel"  },  "359": {    "ID": 359,    "BANK LIST": "American Express",    "Retail Category": "Use Subtype Rules for Categories"  },  "360": {    "ID": 360,    "BANK LIST": "Amoco Corporation",    "Retail Category": "Gasoline/Fuel"  },  "361": {    "ID": 361,    "BANK LIST": "FTD Companies Inc.",    "Retail Category": "Gifts"  },  "362": {    "ID": 362,    "BANK LIST": "Zara",    "Retail Category": "Clothing/Shoes"  },  "363": {    "ID": 363,    "BANK LIST": "Ampco System Parking",    "Retail Category": "Travel"  },  "364": {    "ID": 364,    "BANK LIST": "Shaw's",    "Retail Category": "Groceries"  },  "365": {    "ID": 365,    "BANK LIST": "Dillons",    "Retail Category": "Groceries"  },  "366": {    "ID": 366,    "BANK LIST": "Boston Market",    "Retail Category": "Restaurants/Dining"  },  "367": {    "ID": 367,    "BANK LIST": "The Vitamin Shoppe",    "Retail Category": "Healthcare/Medical"  },  "368": {    "ID": 368,    "BANK LIST": "Carl's Jr.",    "Retail Category": "Restaurants/Dining"  },  "369": {    "ID": 369,    "BANK LIST": "Murphy Oil",    "Retail Category": "Gasoline/Fuel"  },  "370": {    "ID": 370,    "BANK LIST": "Avanti Markets",    "Retail Category": "Groceries"  },  "371": {    "ID": 371,    "BANK LIST": "Weis Markets",    "Retail Category": "Groceries"  },  "372": {    "ID": 372,    "BANK LIST": "Piggly Wiggly",    "Retail Category": "Groceries"  },  "373": {    "ID": 373,    "BANK LIST": "Waffle House",    "Retail Category": "Restaurants/Dining"  },  "374": {    "ID": 374,    "BANK LIST": "Auntie Anne's",    "Retail Category": "Restaurants/Dining"  },  "375": {    "ID": 375,    "BANK LIST": "Caribou Coffee",    "Retail Category": "Restaurants/Dining"  },  "376": {    "ID": 376,    "BANK LIST": "The Coffee Bean",    "Retail Category": "Restaurants/Dining"  },  "377": {    "ID": 377,    "BANK LIST": "Orchard Supply Hardware",    "Retail Category": "Home Maintenance"  },  "378": {    "ID": 378,    "BANK LIST": "Cablevision",    "Retail Category": "Cable/Satellite Services"  },  "379": {    "ID": 379,    "BANK LIST": "Cold Stone Creamery",    "Retail Category": "Restaurants/Dining"  },  "380": {    "ID": 380,    "BANK LIST": "Epoch Payment Solutions",    "Retail Category": "Online Services"  },  "381": {    "ID": 381,    "BANK LIST": "Public Service Enterprise Group",    "Retail Category": "Utilities"  },  "382": {    "ID": 382,    "BANK LIST": "BI-LO",    "Retail Category": "Groceries"  },  "383": {    "ID": 383,    "BANK LIST": "Farm Fresh Food & Pharmacy",    "Retail Category": "Groceries"  },  "384": {    "ID": 384,    "BANK LIST": "Virgin Mobile",    "Retail Category": "Telephone Services"  },  "385": {    "ID": 385,    "BANK LIST": "Century 21 Real Estate",    "Retail Category": "Other Expenses"  },  "386": {    "ID": 386,    "BANK LIST": "Charter Communications",    "Retail Category": "Telephone Services"  },  "387": {    "ID": 387,    "BANK LIST": "Lockheed Martin",    "Retail Category": "Business Miscellaneous"  },  "388": {    "ID": 388,    "BANK LIST": "King Kullen",    "Retail Category": "Groceries"  },  "389": {    "ID": 389,    "BANK LIST": "Tim Hortons",    "Retail Category": "Restaurants/Dining"  },  "390": {    "ID": 390,    "BANK LIST": "Stein Mart",    "Retail Category": "General Merchandise"  },  "391": {    "ID": 391,    "BANK LIST": "Urban Outfitters",    "Retail Category": "Clothing/Shoes"  },  "392": {    "ID": 392,    "BANK LIST": "Cumberland Farms",    "Retail Category": "Groceries"  },  "393": {    "ID": 393,    "BANK LIST": "Bojangles",    "Retail Category": "Restaurants/Dining"  },  "394": {    "ID": 394,    "BANK LIST": "Denny's",    "Retail Category": "Restaurants/Dining"  },  "395": {    "ID": 395,    "BANK LIST": "Bank of America",    "Retail Category": "Use Subtype Rules for Categories"  },  "396": {    "ID": 396,    "BANK LIST": "Casey's General Stores",    "Retail Category": "General Merchandise"  },  "397": {    "ID": 397,    "BANK LIST": "Steak 'n Shake",    "Retail Category": "Restaurants/Dining"  },  "398": {    "ID": 398,    "BANK LIST": "Tuesday Morning",    "Retail Category": "Home Improvement"  },  "399": {    "ID": 399,    "BANK LIST": "Canteen of Coastal California",    "Retail Category": "Restaurants/Dining"  },  "400": {    "ID": 400,    "BANK LIST": "Taco Cabana",    "Retail Category": "Restaurants/Dining"  },  "401": {    "ID": 401,    "BANK LIST": "Citigroup",    "Retail Category": "Use Subtype Rules for Categories"  },  "402": {    "ID": 402,    "BANK LIST": "Kirkland's",    "Retail Category": "General Merchandise"  },  "403": {    "ID": 403,    "BANK LIST": "Aeropostale",    "Retail Category": "Clothing/Shoes"  },  "404": {    "ID": 404,    "BANK LIST": "eBay Inc.",    "Retail Category": "General Merchandise"  },  "405": {    "ID": 405,    "BANK LIST": "Del Taco",    "Retail Category": "Restaurants/Dining"  },  "406": {    "ID": 406,    "BANK LIST": "Market Basket",    "Retail Category": "Groceries"  },  "407": {    "ID": 407,    "BANK LIST": "BevMo!",    "Retail Category": "Groceries"  },  "408": {    "ID": 408,    "BANK LIST": "Claire's",    "Retail Category": "Clothing/Shoes"  },  "409": {    "ID": 409,    "BANK LIST": "Loaf 'N Jug",    "Retail Category": "Groceries"  },  "410": {    "ID": 410,    "BANK LIST": "Edward Jones",    "Retail Category": "Securities Trades"  },  "411": {    "ID": 411,    "BANK LIST": "Lyft",    "Retail Category": "Travel"  },  "412": {    "ID": 412,    "BANK LIST": "Sport Clips",    "Retail Category": "Personal Care"  },  "413": {    "ID": 413,    "BANK LIST": "Pep Boys",    "Retail Category": "Automotive Expenses"  },  "414": {    "ID": 414,    "BANK LIST": "Cabela's",    "Retail Category": "Hobbies"  },  "415": {    "ID": 415,    "BANK LIST": "Shop 'n Save",    "Retail Category": "Groceries"  },  "416": {    "ID": 416,    "BANK LIST": "Famous Footwear",    "Retail Category": "Clothing/Shoes"  },  "417": {    "ID": 417,    "BANK LIST": "Scholastic Corporation",    "Retail Category": "Hobbies"  },  "418": {    "ID": 418,    "BANK LIST": "Smoothie King",    "Retail Category": "Restaurants/Dining"  },  "419": {    "ID": 419,    "BANK LIST": "Jiffy Lube",    "Retail Category": "Automotive Expenses"  },  "420": {    "ID": 420,    "BANK LIST": "Vistaprint",    "Retail Category": "Office Supplies"  },  "421": {    "ID": 421,    "BANK LIST": "Hooters",    "Retail Category": "Restaurants/Dining"  },  "422": {    "ID": 422,    "BANK LIST": "Le Pain Quotidien",    "Retail Category": "Restaurants/Dining"  },  "423": {    "ID": 423,    "BANK LIST": "Adobe Systems",    "Retail Category": "Online Services"  },  "424": {    "ID": 424,    "BANK LIST": "Pick 'n Save",    "Retail Category": "Groceries"  },  "425": {    "ID": 425,    "BANK LIST": "Fiesta Mart",    "Retail Category": "Groceries"  },  "426": {    "ID": 426,    "BANK LIST": "Buy Buy Baby",    "Retail Category": "Child/Dependent Expenses"  },  "427": {    "ID": 427,    "BANK LIST": "Disney Store",    "Retail Category": "General Merchandise"  },  "428": {    "ID": 428,    "BANK LIST": "Food 4 Less",    "Retail Category": "Groceries"  },  "429": {    "ID": 429,    "BANK LIST": "Pinkberry",    "Retail Category": "Restaurants/Dining"  },  "430": {    "ID": 430,    "BANK LIST": "Planet Fitness",    "Retail Category": "Personal Care"  },  "431": {    "ID": 431,    "BANK LIST": "Cox Communications",    "Retail Category": "Cable/Satellite Services"  },  "432": {    "ID": 432,    "BANK LIST": "Allstate",    "Retail Category": "Insurance"  },  "433": {    "ID": 433,    "BANK LIST": "LongHorn Steakhouse",    "Retail Category": "Restaurants/Dining"  },  "434": {    "ID": 434,    "BANK LIST": "Morton Williams",    "Retail Category": "Groceries"  },  "435": {    "ID": 435,    "BANK LIST": "Cost Plus World Market",    "Retail Category": "Home Improvement"  },  "436": {    "ID": 436,    "BANK LIST": "Maverik",    "Retail Category": "Hobbies"  },  "437": {    "ID": 437,    "BANK LIST": "Quick Chek",    "Retail Category": "Groceries"  },  "438": {    "ID": 438,    "BANK LIST": "Firestone",    "Retail Category": "Automotive Expenses"  },  "439": {    "ID": 439,    "BANK LIST": "Save Mart",    "Retail Category": "Groceries"  },  "440": {    "ID": 440,    "BANK LIST": "Equifax",    "Retail Category": "Online Services"  },  "441": {    "ID": 441,    "BANK LIST": "Monitronics",    "Retail Category": "Home Maintenance"  },  "442": {    "ID": 442,    "BANK LIST": "Ford Motor Company",    "Retail Category": "Automotive Expenses"  },  "443": {    "ID": 443,    "BANK LIST": "Saks Fifth Avenue",    "Retail Category": "Clothing/Shoes"  },  "444": {    "ID": 444,    "BANK LIST": "Yard House",    "Retail Category": "Restaurants/Dining"  },  "445": {    "ID": 445,    "BANK LIST": "Modell's",    "Retail Category": "Hobbies"  },  "446": {    "ID": 446,    "BANK LIST": "Braum's",    "Retail Category": "Restaurants/Dining"  },  "447": {    "ID": 447,    "BANK LIST": "Smashburger",    "Retail Category": "Restaurants/Dining"  },  "448": {    "ID": 448,    "BANK LIST": "Big Y",    "Retail Category": "Groceries"  },  "449": {    "ID": 449,    "BANK LIST": "Kum & Go",    "Retail Category": "Groceries"  },  "450": {    "ID": 450,    "BANK LIST": "New York Life Insurance Company",    "Retail Category": "Insurance"  },  "451": {    "ID": 451,    "BANK LIST": "Sbarro",    "Retail Category": "Restaurants/Dining"  },  "452": {    "ID": 452,    "BANK LIST": "Big 5 Sporting Goods",    "Retail Category": "Hobbies"  },  "453": {    "ID": 453,    "BANK LIST": "Bonefish Grill",    "Retail Category": "Restaurants/Dining"  },  "454": {    "ID": 454,    "BANK LIST": "Baskin-Robbins",    "Retail Category": "Restaurants/Dining"  },  "455": {    "ID": 455,    "BANK LIST": "Golden Corral",    "Retail Category": "Restaurants/Dining"  },  "456": {    "ID": 456,    "BANK LIST": "Bass Pro Shops",    "Retail Category": "Hobbies"  },  "457": {    "ID": 457,    "BANK LIST": "Penn Station East Coast Subs",    "Retail Category": "Restaurants/Dining"  },  "458": {    "ID": 458,    "BANK LIST": "Proactiv",    "Retail Category": "Personal Care"  },  "459": {    "ID": 459,    "BANK LIST": "Krispy Kreme",    "Retail Category": "Restaurants/Dining"  },  "460": {    "ID": 460,    "BANK LIST": "99 Cents Only Stores",    "Retail Category": "General Merchandise"  },  "461": {    "ID": 461,    "BANK LIST": "A.C. Moore",    "Retail Category": "Hobbies"  },  "462": {    "ID": 462,    "BANK LIST": "Fine Fare",    "Retail Category": "Groceries"  },  "463": {    "ID": 463,    "BANK LIST": "AAA Insurance",    "Retail Category": "Insurance"  },  "464": {    "ID": 464,    "BANK LIST": "ABC Stores",    "Retail Category": "Groceries"  },  "465": {    "ID": 465,    "BANK LIST": "Aetna",    "Retail Category": "Healthcare/Medical"  },  "466": {    "ID": 466,    "BANK LIST": "Aldo",    "Retail Category": "Clothing/Shoes"  },  "467": {    "ID": 467,    "BANK LIST": "Allsup's",    "Retail Category": "Groceries"  },  "468": {    "ID": 468,    "BANK LIST": "Southwest Gas",    "Retail Category": "Utilities"  },  "469": {    "ID": 469,    "BANK LIST": "Wienerschnitzel",    "Retail Category": "Restaurants/Dining"  },  "470": {    "ID": 470,    "BANK LIST": "Duke Energy",    "Retail Category": "Utilities"  },  "471": {    "ID": 471,    "BANK LIST": "Anytime Fitness",    "Retail Category": "Personal Care"  },  "472": {    "ID": 472,    "BANK LIST": "ARCO",    "Retail Category": "Gasoline/Fuel"  },  "473": {    "ID": 473,    "BANK LIST": "Fingerhut",    "Retail Category": "General Merchandise"  },  "474": {    "ID": 474,    "BANK LIST": "Freddy's Frozen Custard & Steakburgers",    "Retail Category": "Restaurants/Dining"  },  "475": {    "ID": 475,    "BANK LIST": "ALDI",    "Retail Category": "Groceries"  },  "476": {    "ID": 476,    "BANK LIST": "Sweetbay Supermarket",    "Retail Category": "Groceries"  },  "477": {    "ID": 477,    "BANK LIST": "BMW",    "Retail Category": "Automotive Expenses"  },  "478": {    "ID": 478,    "BANK LIST": "FirstEnergy",    "Retail Category": "Utilities"  },  "479": {    "ID": 479,    "BANK LIST": "Freebirds World Burrito",    "Retail Category": "Restaurants/Dining"  },  "480": {    "ID": 480,    "BANK LIST": "Fas Mart",    "Retail Category": "Groceries"  },  "481": {    "ID": 481,    "BANK LIST": "White Castle",    "Retail Category": "Restaurants/Dining"  },  "482": {    "ID": 482,    "BANK LIST": "Suddenlink Communications",    "Retail Category": "Cable/Satellite Services"  },  "483": {    "ID": 483,    "BANK LIST": "Which Wich",    "Retail Category": "Restaurants/Dining"  },  "484": {    "ID": 484,    "BANK LIST": "Turkey Hill Dairy",    "Retail Category": "Groceries"  },  "485": {    "ID": 485,    "BANK LIST": "Connecticut Light & Power",    "Retail Category": "Utilities"  },  "486": {    "ID": 486,    "BANK LIST": "Pita Pit",    "Retail Category": "Restaurants/Dining"  },  "487": {    "ID": 487,    "BANK LIST": "TXU Energy",    "Retail Category": "Utilities"  },  "488": {    "ID": 488,    "BANK LIST": "El Pollo Loco",    "Retail Category": "Restaurants/Dining"  },  "489": {    "ID": 489,    "BANK LIST": "Famous Dave's",    "Retail Category": "Restaurants/Dining"  },  "490": {    "ID": 490,    "BANK LIST": "Fantastic Sams",    "Retail Category": "Personal Care"  },  "491": {    "ID": 491,    "BANK LIST": "Food Maxx",    "Retail Category": "Groceries"  },  "492": {    "ID": 492,    "BANK LIST": "Vivint",    "Retail Category": "Home Maintenance"  },  "493": {    "ID": 493,    "BANK LIST": "Pollo Tropical",    "Retail Category": "Restaurants/Dining"  },  "494": {    "ID": 494,    "BANK LIST": "Redner's Markets",    "Retail Category": "Groceries"  },  "495": {    "ID": 495,    "BANK LIST": "Schlotzsky's",    "Retail Category": "Restaurants/Dining"  },  "496": {    "ID": 496,    "BANK LIST": "Six Flags",    "Retail Category": "Entertainment"  },  "497": {    "ID": 497,    "BANK LIST": "CPS Energy",    "Retail Category": "Utilities"  },  "498": {    "ID": 498,    "BANK LIST": "Pavilions",    "Retail Category": "Groceries"  },  "499": {    "ID": 499,    "BANK LIST": "Quest Diagnostics",    "Retail Category": "Healthcare/Medical"  },  "500": {    "ID": 500,    "BANK LIST": "Sainsbury's",    "Retail Category": "Groceries"  },  "501": {    "ID": 501,    "BANK LIST": "Sarku Japan",    "Retail Category": "Restaurants/Dining"  },  "502": {    "ID": 502,    "BANK LIST": "Washington Gas",    "Retail Category": "Utilities"  },  "503": {    "ID": 503,    "BANK LIST": "Wet Seal",    "Retail Category": "Clothing/Shoes"  },  "504": {    "ID": 504,    "BANK LIST": "Philadelphia Parking Authority",    "Retail Category": "Travel"  },  "505": {    "ID": 505,    "BANK LIST": "Geek Squad",    "Retail Category": "Electronics"  },  "506": {    "ID": 506,    "BANK LIST": "Tops Markets",    "Retail Category": "Groceries"  },  "507": {    "ID": 507,    "BANK LIST": "Georgia Power",    "Retail Category": "Utilities"  },  "508": {    "ID": 508,    "BANK LIST": "Alabama Power",    "Retail Category": "Utilities"  },  "509": {    "ID": 509,    "BANK LIST": "Nissan",    "Retail Category": "Automotive Expenses"  },  "510": {    "ID": 510,    "BANK LIST": "Cheddar's Casual Cafe",    "Retail Category": "Restaurants/Dining"  },  "511": {    "ID": 511,    "BANK LIST": "Commonwealth Edison",    "Retail Category": "Utilities"  },  "512": {    "ID": 512,    "BANK LIST": "Dave & Buster's",    "Retail Category": "Restaurants/Dining"  },  "513": {    "ID": 513,    "BANK LIST": "Cinnabon",    "Retail Category": "Restaurants/Dining"  },  "514": {    "ID": 514,    "BANK LIST": "Safeco Insurance",    "Retail Category": "Insurance"  },  "515": {    "ID": 515,    "BANK LIST": "Checkers",    "Retail Category": "Restaurants/Dining"  },  "516": {    "ID": 516,    "BANK LIST": "Blockbuster",    "Retail Category": "Entertainment"  },  "517": {    "ID": 517,    "BANK LIST": "Baja Fresh",    "Retail Category": "Restaurants/Dining"  },  "518": {    "ID": 518,    "BANK LIST": "Met Foods",    "Retail Category": "Groceries"  },  "519": {    "ID": 519,    "BANK LIST": "WinCo Foods",    "Retail Category": "Groceries"  },  "520": {    "ID": 520,    "BANK LIST": "Hungry Howie's Pizza",    "Retail Category": "Restaurants/Dining"  },  "521": {    "ID": 521,    "BANK LIST": "C_Town Supermarkets",    "Retail Category": "Groceries"  },  "522": {    "ID": 522,    "BANK LIST": "Books-A-Million",    "Retail Category": "Hobbies"  },  "523": {    "ID": 523,    "BANK LIST": "Cici's Pizza",    "Retail Category": "Restaurants/Dining"  },  "524": {    "ID": 524,    "BANK LIST": "Buc-ee's",    "Retail Category": "General Merchandise"  },  "525": {    "ID": 525,    "BANK LIST": "Nicor Gas",    "Retail Category": "Utilities"  },  "526": {    "ID": 526,    "BANK LIST": "GE Capital",    "Retail Category": "Use Subtype Rules for Categories"  },  "527": {    "ID": 527,    "BANK LIST": "Chuy's",    "Retail Category": "Restaurants/Dining"  },  "528": {    "ID": 528,    "BANK LIST": "Crossfit",    "Retail Category": "Personal Care"  },  "529": {    "ID": 529,    "BANK LIST": "Fuddruckers",    "Retail Category": "Restaurants/Dining"  },  "530": {    "ID": 530,    "BANK LIST": "Mellow Mushroom",    "Retail Category": "Restaurants/Dining"  },  "531": {    "ID": 531,    "BANK LIST": "Flash Foods",    "Retail Category": "Groceries"  },  "532": {    "ID": 532,    "BANK LIST": "San Diego Gas & Electric",    "Retail Category": "Utilities"  },  "533": {    "ID": 533,    "BANK LIST": "Zales",    "Retail Category": "Clothing/Shoes"  },  "534": {    "ID": 534,    "BANK LIST": "PECO",    "Retail Category": "Utilities"  },  "535": {    "ID": 535,    "BANK LIST": "Farmers Insurance",    "Retail Category": "Insurance"  },  "536": {    "ID": 536,    "BANK LIST": "Dierbergs Markets",    "Retail Category": "Healthcare/Medical"  },  "537": {    "ID": 537,    "BANK LIST": "American Funds",    "Retail Category": "Use Subtype Rules for Categories"  },  "538": {    "ID": 538,    "BANK LIST": "Northwestern Mutual",    "Retail Category": "Use Subtype Rules for Categories"  },  "539": {    "ID": 539,    "BANK LIST": "Church's Chicken",    "Retail Category": "Restaurants/Dining"  },  "540": {    "ID": 540,    "BANK LIST": "Raising Cane's",    "Retail Category": "Restaurants/Dining"  },  "541": {    "ID": 541,    "BANK LIST": "Texas OAG Child Support",    "Retail Category": "Child/Dependent Expenses"  },  "542": {    "ID": 542,    "BANK LIST": "Lifetouch",    "Retail Category": "Gifts"  },  "543": {    "ID": 543,    "BANK LIST": "Associated Supermarkets",    "Retail Category": "Groceries"  },  "544": {    "ID": 544,    "BANK LIST": "Consumers Energy",    "Retail Category": "Utilities"  },  "545": {    "ID": 545,    "BANK LIST": "Atmos Energy",    "Retail Category": "Utilities"  },  "546": {    "ID": 546,    "BANK LIST": "SmartStyle",    "Retail Category": "Personal Care"  },  "547": {    "ID": 547,    "BANK LIST": "Xcel Energy",    "Retail Category": "Utilities"  },  "548": {    "ID": 548,    "BANK LIST": "BART",    "Retail Category": "Travel"  },  "549": {    "ID": 549,    "BANK LIST": "Bashas' Supermarkets",    "Retail Category": "Groceries"  },  "550": {    "ID": 550,    "BANK LIST": "Bill Miller Bar-B-Q",    "Retail Category": "Restaurants/Dining"  },  "551": {    "ID": 551,    "BANK LIST": "Bob Evans",    "Retail Category": "Restaurants/Dining"  },  "552": {    "ID": 552,    "BANK LIST": "Primerica",    "Retail Category": "Use Subtype Rules for Categories"  },  "553": {    "ID": 553,    "BANK LIST": "Boost Mobile",    "Retail Category": "Telephone Services"  },  "554": {    "ID": 554,    "BANK LIST": "Ricker's",    "Retail Category": "Groceries"  },  "555": {    "ID": 555,    "BANK LIST": "Bright House Networks",    "Retail Category": "Cable/Satellite Services"  },  "556": {    "ID": 556,    "BANK LIST": "Lincoln Benefit Life",    "Retail Category": "Insurance"  },  "557": {    "ID": 557,    "BANK LIST": "Wingstop",    "Retail Category": "Restaurants/Dining"  },  "558": {    "ID": 558,    "BANK LIST": "Five Below",    "Retail Category": "General Merchandise"  },  "559": {    "ID": 559,    "BANK LIST": "Portillo's",    "Retail Category": "Restaurants/Dining"  },  "560": {    "ID": 560,    "BANK LIST": "Tesco",    "Retail Category": "General Merchandise"  },  "561": {    "ID": 561,    "BANK LIST": "Blue Cross Blue Shield Association",    "Retail Category": "Insurance"  },  "562": {    "ID": 562,    "BANK LIST": "Puget Sound Energy",    "Retail Category": "Utilities"  },  "563": {    "ID": 563,    "BANK LIST": "Luby's Cafe",    "Retail Category": "Restaurants/Dining"  },  "564": {    "ID": 564,    "BANK LIST": "MetroPCS",    "Retail Category": "Telephone Services"  },  "565": {    "ID": 565,    "BANK LIST": "Lane Bryant",    "Retail Category": "Clothing/Shoes"  },  "566": {    "ID": 566,    "BANK LIST": "H&R Block",    "Retail Category": "Taxes"  },  "567": {    "ID": 567,    "BANK LIST": "Carmike Cinemas",    "Retail Category": "Entertainment"  },  "568": {    "ID": 568,    "BANK LIST": "Cook Out",    "Retail Category": "Restaurants/Dining"  },  "569": {    "ID": 569,    "BANK LIST": "ACS Education Services",    "Retail Category": "Education"  },  "570": {    "ID": 570,    "BANK LIST": "Dickey's Barbecue Pit",    "Retail Category": "Restaurants/Dining"  },  "571": {    "ID": 571,    "BANK LIST": "Earth Fare",    "Retail Category": "Groceries"  },  "572": {    "ID": 572,    "BANK LIST": "Finish Line",    "Retail Category": "Clothing/Shoes"  },  "573": {    "ID": 573,    "BANK LIST": "Food City",    "Retail Category": "Groceries"  },  "574": {    "ID": 574,    "BANK LIST": "Foot Locker",    "Retail Category": "Clothing/Shoes"  },  "575": {    "ID": 575,    "BANK LIST": "Columbia Gas",    "Retail Category": "Utilities"  },  "576": {    "ID": 576,    "BANK LIST": "PG&E",    "Retail Category": "Utilities"  },  "577": {    "ID": 577,    "BANK LIST": "American Family Insurance",    "Retail Category": "Insurance"  },  "578": {    "ID": 578,    "BANK LIST": "United Dairy Farmers",    "Retail Category": "Groceries"  },  "579": {    "ID": 579,    "BANK LIST": "O'Charley's",    "Retail Category": "Restaurants/Dining"  },  "580": {    "ID": 580,    "BANK LIST": "Pepco",    "Retail Category": "Utilities"  },  "581": {    "ID": 581,    "BANK LIST": "CenterPoint Energy",    "Retail Category": "Utilities"  },  "582": {    "ID": 582,    "BANK LIST": "Save-A-Lot",    "Retail Category": "Groceries"  },  "583": {    "ID": 583,    "BANK LIST": "Southern California Edison",    "Retail Category": "Utilities"  },  "584": {    "ID": 584,    "BANK LIST": "Spencer's",    "Retail Category": "Gifts"  },  "585": {    "ID": 585,    "BANK LIST": "Taco Bueno",    "Retail Category": "Restaurants/Dining"  },  "586": {    "ID": 586,    "BANK LIST": "Vonage",    "Retail Category": "Telephone Services"  },  "587": {    "ID": 587,    "BANK LIST": "American Water",    "Retail Category": "Utilities"  },  "588": {    "ID": 588,    "BANK LIST": "Tesoro",    "Retail Category": "Gasoline/Fuel"  },  "589": {    "ID": 589,    "BANK LIST": "NSTAR",    "Retail Category": "Utilities"  },  "590": {    "ID": 590,    "BANK LIST": "Food Town",    "Retail Category": "Groceries"  },  "591": {    "ID": 591,    "BANK LIST": "FoodLand",    "Retail Category": "Groceries"  },  "592": {    "ID": 592,    "BANK LIST": "Nevada Power Company",    "Retail Category": "Utilities"  },  "593": {    "ID": 593,    "BANK LIST": "Shipley Do-Nuts",    "Retail Category": "Restaurants/Dining"  },  "594": {    "ID": 594,    "BANK LIST": "Dominion Virginia Power",    "Retail Category": "Utilities"  },  "595": {    "ID": 595,    "BANK LIST": "Reliant Energy",    "Retail Category": "Utilities"  },  "596": {    "ID": 596,    "BANK LIST": "Scentsy",    "Retail Category": "Gifts"  },  "597": {    "ID": 597,    "BANK LIST": "Stewart's Shops",    "Retail Category": "Groceries"  },  "598": {    "ID": 598,    "BANK LIST": "TransUnion",    "Retail Category": "Online Services"  },  "599": {    "ID": 599,    "BANK LIST": "Gerber Life Insurance Company",    "Retail Category": "Insurance"  },  "600": {    "ID": 600,    "BANK LIST": "Southern California Gas Company",    "Retail Category": "Utilities"  },  "601": {    "ID": 601,    "BANK LIST": "Transamerica",    "Retail Category": "Insurance"  },  "602": {    "ID": 602,    "BANK LIST": "On the Border",    "Retail Category": "Restaurants/Dining"  },  "603": {    "ID": 603,    "BANK LIST": "Prudential Financial",    "Retail Category": "Insurance"  },  "604": {    "ID": 604,    "BANK LIST": "DTE Energy",    "Retail Category": "Utilities"  },  "605": {    "ID": 605,    "BANK LIST": "CenturyLink",    "Retail Category": "Cable/Satellite Services"  },  "606": {    "ID": 606,    "BANK LIST": "Dutch Bros. Coffee",    "Retail Category": "Restaurants/Dining"  },  "607": {    "ID": 607,    "BANK LIST": "Con Edison",    "Retail Category": "Utilities"  }}